gain_imputer/__init__.py
gain_imputer/discriminator.py
gain_imputer/gain_model.py
gain_imputer/generator.py
gain_imputer/imputer.py
gain_imputer/imputer_builder.py
gain_imputer/utils.py
gain_imputer-0.0.103.dist-info/METADATA
gain_imputer-0.0.103.dist-info/WHEEL
gain_imputer-0.0.103.dist-info/licenses/LICENSE
gain_imputer-0.0.103.dist-info/RECORD
