Metadata-Version: 2.1
Name: gain-imputer
Version: 0.0.103
Summary: Missing tabular data imputation using GANs
Project-URL: Homepage, https://github.com/Jagac/gain-imputer
Author-email: Jagac <jagac41@gmail.com>
License-Expression: MIT
License-File: LICENSE
Classifier: License :: OSI Approved :: MIT License
Classifier: Operating System :: OS Independent
Classifier: Programming Language :: Python :: 3.10
Requires-Python: >=3.8
Requires-Dist: numpy>=1.26.2
Requires-Dist: torch>=2.1.2
Requires-Dist: tqdm>=4.66.1
